LICENSE
MANIFEST.in
README.md
setup.cfg
setup.py
versioneer.py
src/kabaret/__init__.py
src/kabaret.flow_contextual_dict.egg-info/PKG-INFO
src/kabaret.flow_contextual_dict.egg-info/SOURCES.txt
src/kabaret.flow_contextual_dict.egg-info/dependency_links.txt
src/kabaret.flow_contextual_dict.egg-info/requires.txt
src/kabaret.flow_contextual_dict.egg-info/top_level.txt
src/kabaret/flow_contextual_dict/__init__.py
src/kabaret/flow_contextual_dict/_version.py
src/kabaret/flow_contextual_dict/demo_flow.py
src/kabaret/flow_contextual_dict/objects.py
src/kabaret/flow_contextual_dict/view/__init__.py
src/kabaret/flow_contextual_dict/view/icons/__init__.py
src/kabaret/flow_contextual_dict/view/icons/add.png
src/kabaret/flow_contextual_dict/view/icons/refresh.png
src/kabaret/flow_contextual_dict/view/icons/remove.png