Metadata-Version: 2.4
Name: kabaret.flow_contextual_dict
Version: 0.2.0
Summary: kabaret.flow contextual dict
Home-page: https://gitlab.com/kabaretstudio/kabaret.flow_contextual_dict
Author: Damien "dee" Coureau
Author-email: kabaret-dev@googlegroups.com
License: LGPLv3+
Keywords: vfx animation pipeline asset library
Classifier: Development Status :: 4 - Beta
Classifier: Programming Language :: Python :: 2.7
Classifier: Programming Language :: Python :: 3.7
Classifier: License :: OSI Approved :: GNU Lesser General Public License v3 or later (LGPLv3+)
Requires-Python: >=2.7,!=3.0.*,!=3.1.*,!=3.2.*
License-File: LICENSE
Requires-Dist: kabaret>=2.4.0rc4
Provides-Extra: dev
Requires-Dist: twine; extra == "dev"
Requires-Dist: flake8; extra == "dev"
Requires-Dist: black; extra == "dev"
Dynamic: author
Dynamic: author-email
Dynamic: classifier
Dynamic: description
Dynamic: description-content-type
Dynamic: home-page
Dynamic: keywords
Dynamic: license
Dynamic: license-file
Dynamic: provides-extra
Dynamic: requires-dist
Dynamic: requires-python
Dynamic: summary
